{
    "Workflow": [
        {
            "ScenarioCode": "NW_DP_0008",
            "WorkflowName": "Print Statement of Account",
            "WorkStageName": "",
            "DisplayLayoutRow": "0",
            "DisplayLayoutColumn": "0",
            "LoadingPageType": "Image",
            "KinsPageNumber": "137150",
            "KinsPageName": "Checking Account",
            "WorkStageNameKo": ""
        },
        {
            "ScenarioCode": "NW_DP_0008",
            "WorkflowName": "Print Statement of Account",
            "WorkStageName": "",
            "DisplayLayoutRow": "0",
            "DisplayLayoutColumn": "1",
            "LoadingPageType": "Right",
            "KinsPageNumber": "",
            "KinsPageName": "",
            "WorkStageNameKo": ""
        },
        {
            "ScenarioCode": "NW_DP_0008",
            "WorkflowName": "Print Statement of Account",
            "WorkStageName": "정기 발송 여부 (담당자가 기일 도래 Notice 확인 후 본 화면으로 이동한 경우) ",
            "DisplayLayoutRow": "0",
            "DisplayLayoutColumn": "2",
            "LoadingPageType": "Fork",
            "KinsPageNumber": "",
            "KinsPageName": "",
            "WorkStageNameKo": ""
        },
        {
            "ScenarioCode": "NW_DP_0008",
            "WorkflowName": "Print Statement of Account",
            "WorkStageName": "",
            "DisplayLayoutRow": "0",
            "DisplayLayoutColumn": "3",
            "LoadingPageType": "예",
            "KinsPageNumber": "",
            "KinsPageName": "",
            "WorkStageNameKo": ""
        },
        {
            "ScenarioCode": "NW_DP_0008",
            "WorkflowName": "Print Statement of Account",
            "WorkStageName": "(KR) Status가 \"NORMAL | RENEW\"인 고객 앞 계좌 명세서 일괄 UMS 발송을 위해 일괄 UMS 버튼 클릭  (EN) Press 일괄 UMS button to send statement of account all at once to customers holding accounts that are set with Status as \"NORMAL | RENEW\" ",
            "DisplayLayoutRow": "0",
            "DisplayLayoutColumn": "4",
            "LoadingPageType": "Image",
            "KinsPageNumber": "137150",
            "KinsPageName": "Checking Account",
            "WorkStageNameKo": ""
        },
        {
            "ScenarioCode": "NW_DP_0008",
            "WorkflowName": "Print Statement of Account",
            "WorkStageName": "",
            "DisplayLayoutRow": "0",
            "DisplayLayoutColumn": "5",
            "LoadingPageType": "Right",
            "KinsPageNumber": "",
            "KinsPageName": "",
            "WorkStageNameKo": ""
        },
        {
            "ScenarioCode": "NW_DP_0008",
            "WorkflowName": "Print Statement of Account",
            "WorkStageName": "",
            "DisplayLayoutRow": "0",
            "DisplayLayoutColumn": "6",
            "LoadingPageType": "Image",
            "KinsPageNumber": "UMS",
            "KinsPageName": "",
            "WorkStageNameKo": ""
        },
        {
            "ScenarioCode": "NW_DP_0008",
            "WorkflowName": "Print Statement of Account",
            "WorkStageName": "",
            "DisplayLayoutRow": "0",
            "DisplayLayoutColumn": "7",
            "LoadingPageType": "━",
            "KinsPageNumber": "",
            "KinsPageName": "",
            "WorkStageNameKo": ""
        },
        {
            "ScenarioCode": "NW_DP_0008",
            "WorkflowName": "Print Statement of Account",
            "WorkStageName": "",
            "DisplayLayoutRow": "0",
            "DisplayLayoutColumn": "8",
            "LoadingPageType": "━",
            "KinsPageNumber": "",
            "KinsPageName": "",
            "WorkStageNameKo": ""
        },
        {
            "ScenarioCode": "NW_DP_0008",
            "WorkflowName": "Print Statement of Account",
            "WorkStageName": "",
            "DisplayLayoutRow": "0",
            "DisplayLayoutColumn": "9",
            "LoadingPageType": "━",
            "KinsPageNumber": "",
            "KinsPageName": "",
            "WorkStageNameKo": ""
        },
        {
            "ScenarioCode": "NW_DP_0008",
            "WorkflowName": "Print Statement of Account",
            "WorkStageName": "",
            "DisplayLayoutRow": "0",
            "DisplayLayoutColumn": "10",
            "LoadingPageType": "━",
            "KinsPageNumber": "",
            "KinsPageName": "",
            "WorkStageNameKo": ""
        },
        {
            "ScenarioCode": "NW_DP_0008",
            "WorkflowName": "Print Statement of Account",
            "WorkStageName": "",
            "DisplayLayoutRow": "0",
            "DisplayLayoutColumn": "11",
            "LoadingPageType": "━",
            "KinsPageNumber": "",
            "KinsPageName": "",
            "WorkStageNameKo": ""
        },
        {
            "ScenarioCode": "NW_DP_0008",
            "WorkflowName": "Print Statement of Account",
            "WorkStageName": "",
            "DisplayLayoutRow": "0",
            "DisplayLayoutColumn": "12",
            "LoadingPageType": "┐",
            "KinsPageNumber": "",
            "KinsPageName": "",
            "WorkStageNameKo": ""
        },
        {
            "ScenarioCode": "NW_DP_0008",
            "WorkflowName": "Print Statement of Account",
            "WorkStageName": "",
            "DisplayLayoutRow": "1",
            "DisplayLayoutColumn": "2",
            "LoadingPageType": "노",
            "KinsPageNumber": "",
            "KinsPageName": "",
            "WorkStageNameKo": ""
        },
        {
            "ScenarioCode": "NW_DP_0008",
            "WorkflowName": "Print Statement of Account",
            "WorkStageName": "",
            "DisplayLayoutRow": "1",
            "DisplayLayoutColumn": "4",
            "LoadingPageType": "│",
            "KinsPageNumber": "",
            "KinsPageName": "",
            "WorkStageNameKo": ""
        },
        {
            "ScenarioCode": "NW_DP_0008",
            "WorkflowName": "Print Statement of Account",
            "WorkStageName": "",
            "DisplayLayoutRow": "1",
            "DisplayLayoutColumn": "12",
            "LoadingPageType": "│",
            "KinsPageNumber": "",
            "KinsPageName": "",
            "WorkStageNameKo": ""
        },
        {
            "ScenarioCode": "NW_DP_0008",
            "WorkflowName": "Print Statement of Account",
            "WorkStageName": "",
            "DisplayLayoutRow": "2",
            "DisplayLayoutColumn": "2",
            "LoadingPageType": "│",
            "KinsPageNumber": "",
            "KinsPageName": "",
            "WorkStageNameKo": ""
        },
        {
            "ScenarioCode": "NW_DP_0008",
            "WorkflowName": "Print Statement of Account",
            "WorkStageName": "",
            "DisplayLayoutRow": "2",
            "DisplayLayoutColumn": "4",
            "LoadingPageType": "Picture",
            "KinsPageNumber": "137150",
            "KinsPageName": "",
            "WorkStageNameKo": ""
        },
        {
            "ScenarioCode": "NW_DP_0008",
            "WorkflowName": "Print Statement of Account",
            "WorkStageName": "",
            "DisplayLayoutRow": "2",
            "DisplayLayoutColumn": "12",
            "LoadingPageType": "│",
            "KinsPageNumber": "",
            "KinsPageName": "",
            "WorkStageNameKo": ""
        },
        {
            "ScenarioCode": "NW_DP_0008",
            "WorkflowName": "Print Statement of Account",
            "WorkStageName": "",
            "DisplayLayoutRow": "3",
            "DisplayLayoutColumn": "2",
            "LoadingPageType": "│",
            "KinsPageNumber": "",
            "KinsPageName": "",
            "WorkStageNameKo": ""
        },
        {
            "ScenarioCode": "NW_DP_0008",
            "WorkflowName": "Print Statement of Account",
            "WorkStageName": "",
            "DisplayLayoutRow": "3",
            "DisplayLayoutColumn": "12",
            "LoadingPageType": "│",
            "KinsPageNumber": "",
            "KinsPageName": "",
            "WorkStageNameKo": ""
        },
        {
            "ScenarioCode": "NW_DP_0008",
            "WorkflowName": "Print Statement of Account",
            "WorkStageName": "",
            "DisplayLayoutRow": "4",
            "DisplayLayoutColumn": "2",
            "LoadingPageType": "└",
            "KinsPageNumber": "",
            "KinsPageName": "",
            "WorkStageNameKo": ""
        },
        {
            "ScenarioCode": "NW_DP_0008",
            "WorkflowName": "Print Statement of Account",
            "WorkStageName": "",
            "DisplayLayoutRow": "4",
            "DisplayLayoutColumn": "3",
            "LoadingPageType": "Right",
            "KinsPageNumber": "",
            "KinsPageName": "",
            "WorkStageNameKo": ""
        },
        {
            "ScenarioCode": "NW_DP_0008",
            "WorkflowName": "Print Statement of Account",
            "WorkStageName": "(KR) 조회된 계좌 목록에서 계좌 명세서 발송 대상 계좌를 단건 또는 복수건 선택 (EN) Select one or multiple Accounts From the retrieved Account List to send account Statements ",
            "DisplayLayoutRow": "4",
            "DisplayLayoutColumn": "4",
            "LoadingPageType": "Image",
            "KinsPageNumber": "137150",
            "KinsPageName": "Checking Account",
            "WorkStageNameKo": ""
        },
        {
            "ScenarioCode": "NW_DP_0008",
            "WorkflowName": "Print Statement of Account",
            "WorkStageName": "",
            "DisplayLayoutRow": "4",
            "DisplayLayoutColumn": "5",
            "LoadingPageType": "Right",
            "KinsPageNumber": "",
            "KinsPageName": "",
            "WorkStageNameKo": ""
        },
        {
            "ScenarioCode": "NW_DP_0008",
            "WorkflowName": "Print Statement of Account",
            "WorkStageName": "UMS 발송 여부 ",
            "DisplayLayoutRow": "4",
            "DisplayLayoutColumn": "6",
            "LoadingPageType": "Fork",
            "KinsPageNumber": "",
            "KinsPageName": "",
            "WorkStageNameKo": ""
        },
        {
            "ScenarioCode": "NW_DP_0008",
            "WorkflowName": "Print Statement of Account",
            "WorkStageName": "",
            "DisplayLayoutRow": "4",
            "DisplayLayoutColumn": "7",
            "LoadingPageType": "예",
            "KinsPageNumber": "",
            "KinsPageName": "",
            "WorkStageNameKo": ""
        },
        {
            "ScenarioCode": "NW_DP_0008",
            "WorkflowName": "Print Statement of Account",
            "WorkStageName": "",
            "DisplayLayoutRow": "4",
            "DisplayLayoutColumn": "8",
            "LoadingPageType": "Image",
            "KinsPageNumber": "137150",
            "KinsPageName": "Checking Account",
            "WorkStageNameKo": ""
        },
        {
            "ScenarioCode": "NW_DP_0008",
            "WorkflowName": "Print Statement of Account",
            "WorkStageName": "",
            "DisplayLayoutRow": "4",
            "DisplayLayoutColumn": "9",
            "LoadingPageType": "Right",
            "KinsPageNumber": "",
            "KinsPageName": "",
            "WorkStageNameKo": ""
        },
        {
            "ScenarioCode": "NW_DP_0008",
            "WorkflowName": "Print Statement of Account",
            "WorkStageName": "",
            "DisplayLayoutRow": "4",
            "DisplayLayoutColumn": "10",
            "LoadingPageType": "Image",
            "KinsPageNumber": "UMS",
            "KinsPageName": "",
            "WorkStageNameKo": ""
        },
        {
            "ScenarioCode": "NW_DP_0008",
            "WorkflowName": "Print Statement of Account",
            "WorkStageName": "",
            "DisplayLayoutRow": "4",
            "DisplayLayoutColumn": "11",
            "LoadingPageType": "━",
            "KinsPageNumber": "",
            "KinsPageName": "",
            "WorkStageNameKo": ""
        },
        {
            "ScenarioCode": "NW_DP_0008",
            "WorkflowName": "Print Statement of Account",
            "WorkStageName": "",
            "DisplayLayoutRow": "4",
            "DisplayLayoutColumn": "12",
            "LoadingPageType": "┤",
            "KinsPageNumber": "",
            "KinsPageName": "",
            "WorkStageNameKo": ""
        },
        {
            "ScenarioCode": "NW_DP_0008",
            "WorkflowName": "Print Statement of Account",
            "WorkStageName": "",
            "DisplayLayoutRow": "5",
            "DisplayLayoutColumn": "6",
            "LoadingPageType": "노",
            "KinsPageNumber": "",
            "KinsPageName": "",
            "WorkStageNameKo": ""
        },
        {
            "ScenarioCode": "NW_DP_0008",
            "WorkflowName": "Print Statement of Account",
            "WorkStageName": "",
            "DisplayLayoutRow": "5",
            "DisplayLayoutColumn": "8",
            "LoadingPageType": "│",
            "KinsPageNumber": "",
            "KinsPageName": "",
            "WorkStageNameKo": ""
        },
        {
            "ScenarioCode": "NW_DP_0008",
            "WorkflowName": "Print Statement of Account",
            "WorkStageName": "",
            "DisplayLayoutRow": "5",
            "DisplayLayoutColumn": "12",
            "LoadingPageType": "│",
            "KinsPageNumber": "",
            "KinsPageName": "",
            "WorkStageNameKo": ""
        },
        {
            "ScenarioCode": "NW_DP_0008",
            "WorkflowName": "Print Statement of Account",
            "WorkStageName": "",
            "DisplayLayoutRow": "6",
            "DisplayLayoutColumn": "6",
            "LoadingPageType": "│",
            "KinsPageNumber": "",
            "KinsPageName": "",
            "WorkStageNameKo": ""
        },
        {
            "ScenarioCode": "NW_DP_0008",
            "WorkflowName": "Print Statement of Account",
            "WorkStageName": "",
            "DisplayLayoutRow": "6",
            "DisplayLayoutColumn": "8",
            "LoadingPageType": "Picture",
            "KinsPageNumber": "137150",
            "KinsPageName": "",
            "WorkStageNameKo": ""
        },
        {
            "ScenarioCode": "NW_DP_0008",
            "WorkflowName": "Print Statement of Account",
            "WorkStageName": "",
            "DisplayLayoutRow": "6",
            "DisplayLayoutColumn": "12",
            "LoadingPageType": "│",
            "KinsPageNumber": "",
            "KinsPageName": "",
            "WorkStageNameKo": ""
        },
        {
            "ScenarioCode": "NW_DP_0008",
            "WorkflowName": "Print Statement of Account",
            "WorkStageName": "",
            "DisplayLayoutRow": "7",
            "DisplayLayoutColumn": "6",
            "LoadingPageType": "Down",
            "KinsPageNumber": "",
            "KinsPageName": "",
            "WorkStageNameKo": ""
        },
        {
            "ScenarioCode": "NW_DP_0008",
            "WorkflowName": "Print Statement of Account",
            "WorkStageName": "",
            "DisplayLayoutRow": "7",
            "DisplayLayoutColumn": "12",
            "LoadingPageType": "│",
            "KinsPageNumber": "",
            "KinsPageName": "",
            "WorkStageNameKo": ""
        },
        {
            "ScenarioCode": "NW_DP_0008",
            "WorkflowName": "Print Statement of Account",
            "WorkStageName": "(KR) 선택된 계좌 명세서 발송 대상 계좌 확인 후 Print 버튼 클릭 (EN) After Confirming the Selected Accounts For Sending Account Statements, Click The PRINT Button.  ",
            "DisplayLayoutRow": "8",
            "DisplayLayoutColumn": "6",
            "LoadingPageType": "Image",
            "KinsPageNumber": "137150",
            "KinsPageName": "Checking Account",
            "WorkStageNameKo": ""
        },
        {
            "ScenarioCode": "NW_DP_0008",
            "WorkflowName": "Print Statement of Account",
            "WorkStageName": "",
            "DisplayLayoutRow": "8",
            "DisplayLayoutColumn": "7",
            "LoadingPageType": "Right",
            "KinsPageNumber": "",
            "KinsPageName": "",
            "WorkStageNameKo": ""
        },
        {
            "ScenarioCode": "NW_DP_0008",
            "WorkflowName": "Print Statement of Account",
            "WorkStageName": "(베이징 지점) MT940 메시지 생성을 통한 계좌명세서 발송 여부 ",
            "DisplayLayoutRow": "8",
            "DisplayLayoutColumn": "8",
            "LoadingPageType": "Fork",
            "KinsPageNumber": "",
            "KinsPageName": "",
            "WorkStageNameKo": ""
        },
        {
            "ScenarioCode": "NW_DP_0008",
            "WorkflowName": "Print Statement of Account",
            "WorkStageName": "",
            "DisplayLayoutRow": "8",
            "DisplayLayoutColumn": "9",
            "LoadingPageType": "예",
            "KinsPageNumber": "",
            "KinsPageName": "",
            "WorkStageNameKo": ""
        },
        {
            "ScenarioCode": "NW_DP_0008",
            "WorkflowName": "Print Statement of Account",
            "WorkStageName": "(KR) MT940 형식에 맞게 내용 항목을 입력하여 메시지 생성 및 SWIFT 전문 발송 (EN) Create MT940 Message by entering content items and process SWIFT message ",
            "DisplayLayoutRow": "8",
            "DisplayLayoutColumn": "10",
            "LoadingPageType": "Image",
            "KinsPageNumber": "137150",
            "KinsPageName": "Checking Account",
            "WorkStageNameKo": ""
        },
        {
            "ScenarioCode": "NW_DP_0008",
            "WorkflowName": "Print Statement of Account",
            "WorkStageName": "",
            "DisplayLayoutRow": "8",
            "DisplayLayoutColumn": "11",
            "LoadingPageType": "━",
            "KinsPageNumber": "",
            "KinsPageName": "",
            "WorkStageNameKo": ""
        },
        {
            "ScenarioCode": "NW_DP_0008",
            "WorkflowName": "Print Statement of Account",
            "WorkStageName": "",
            "DisplayLayoutRow": "8",
            "DisplayLayoutColumn": "12",
            "LoadingPageType": "┤",
            "KinsPageNumber": "",
            "KinsPageName": "",
            "WorkStageNameKo": ""
        },
        {
            "ScenarioCode": "NW_DP_0008",
            "WorkflowName": "Print Statement of Account",
            "WorkStageName": "",
            "DisplayLayoutRow": "9",
            "DisplayLayoutColumn": "6",
            "LoadingPageType": "│",
            "KinsPageNumber": "",
            "KinsPageName": "",
            "WorkStageNameKo": ""
        },
        {
            "ScenarioCode": "NW_DP_0008",
            "WorkflowName": "Print Statement of Account",
            "WorkStageName": "",
            "DisplayLayoutRow": "9",
            "DisplayLayoutColumn": "8",
            "LoadingPageType": "노",
            "KinsPageNumber": "",
            "KinsPageName": "",
            "WorkStageNameKo": ""
        },
        {
            "ScenarioCode": "NW_DP_0008",
            "WorkflowName": "Print Statement of Account",
            "WorkStageName": "",
            "DisplayLayoutRow": "9",
            "DisplayLayoutColumn": "12",
            "LoadingPageType": "Down",
            "KinsPageNumber": "",
            "KinsPageName": "",
            "WorkStageNameKo": ""
        },
        {
            "ScenarioCode": "NW_DP_0008",
            "WorkflowName": "Print Statement of Account",
            "WorkStageName": "",
            "DisplayLayoutRow": "10",
            "DisplayLayoutColumn": "6",
            "LoadingPageType": "Picture",
            "KinsPageNumber": "137150",
            "KinsPageName": "",
            "WorkStageNameKo": ""
        },
        {
            "ScenarioCode": "NW_DP_0008",
            "WorkflowName": "Print Statement of Account",
            "WorkStageName": "",
            "DisplayLayoutRow": "10",
            "DisplayLayoutColumn": "8",
            "LoadingPageType": "└",
            "KinsPageNumber": "",
            "KinsPageName": "",
            "WorkStageNameKo": ""
        },
        {
            "ScenarioCode": "NW_DP_0008",
            "WorkflowName": "Print Statement of Account",
            "WorkStageName": "",
            "DisplayLayoutRow": "10",
            "DisplayLayoutColumn": "9",
            "LoadingPageType": "━",
            "KinsPageNumber": "",
            "KinsPageName": "",
            "WorkStageNameKo": ""
        },
        {
            "ScenarioCode": "NW_DP_0008",
            "WorkflowName": "Print Statement of Account",
            "WorkStageName": "",
            "DisplayLayoutRow": "10",
            "DisplayLayoutColumn": "10",
            "LoadingPageType": "━",
            "KinsPageNumber": "",
            "KinsPageName": "",
            "WorkStageNameKo": ""
        },
        {
            "ScenarioCode": "NW_DP_0008",
            "WorkflowName": "Print Statement of Account",
            "WorkStageName": "",
            "DisplayLayoutRow": "10",
            "DisplayLayoutColumn": "11",
            "LoadingPageType": "Right",
            "KinsPageNumber": "",
            "KinsPageName": "",
            "WorkStageNameKo": ""
        },
        {
            "ScenarioCode": "NW_DP_0008",
            "WorkflowName": "Print Statement of Account",
            "WorkStageName": "",
            "DisplayLayoutRow": "10",
            "DisplayLayoutColumn": "12",
            "LoadingPageType": "End",
            "KinsPageNumber": "",
            "KinsPageName": "",
            "WorkStageNameKo": ""
        },
        {
            "ScenarioCode": "NW_DP_0009",
            "WorkflowName": "Print Customer Balance Statement",
            "WorkStageName": "(KR) 고객 번호, 계좌 번호 등을 기입하고 Inquiry 버튼을 클릭 (EN) Fill in information such as Customer No, Account No and press Inquiry button ",
            "DisplayLayoutRow": "0",
            "DisplayLayoutColumn": "0",
            "LoadingPageType": "Image",
            "KinsPageNumber": "137250",
            "KinsPageName": "Customer Balance Statement",
            "WorkStageNameKo": ""
        },
        {
            "ScenarioCode": "NW_DP_0009",
            "WorkflowName": "Print Customer Balance Statement",
            "WorkStageName": "",
            "DisplayLayoutRow": "0",
            "DisplayLayoutColumn": "1",
            "LoadingPageType": "━",
            "KinsPageNumber": "",
            "KinsPageName": "",
            "WorkStageNameKo": ""
        },
        {
            "ScenarioCode": "NW_DP_0009",
            "WorkflowName": "Print Customer Balance Statement",
            "WorkStageName": "정기 발송 여부 (담당자가 기일 도래 Notice 확인 후 본 화면으로 이동한 경우) ",
            "DisplayLayoutRow": "0",
            "DisplayLayoutColumn": "2",
            "LoadingPageType": "Fork",
            "KinsPageNumber": "",
            "KinsPageName": "",
            "WorkStageNameKo": ""
        },
        {
            "ScenarioCode": "NW_DP_0009",
            "WorkflowName": "Print Customer Balance Statement",
            "WorkStageName": "",
            "DisplayLayoutRow": "0",
            "DisplayLayoutColumn": "3",
            "LoadingPageType": "예",
            "KinsPageNumber": "",
            "KinsPageName": "",
            "WorkStageNameKo": ""
        },
        {
            "ScenarioCode": "NW_DP_0009",
            "WorkflowName": "Print Customer Balance Statement",
            "WorkStageName": "(KR) Status가 \"NORMAL\"인 고객 앞 잔액대사명세서 일괄 UMS 발송을 위해 일괄 UMS 버튼 클릭  (EN) Press 일괄 UMS button to send Customer Balance Statement all at once to customers holding accounts that are set with Status as \"NORMAL\" ",
            "DisplayLayoutRow": "0",
            "DisplayLayoutColumn": "4",
            "LoadingPageType": "Image",
            "KinsPageNumber": "137250",
            "KinsPageName": "Customer Balance Statement",
            "WorkStageNameKo": ""
        },
        {
            "ScenarioCode": "NW_DP_0009",
            "WorkflowName": "Print Customer Balance Statement",
            "WorkStageName": "",
            "DisplayLayoutRow": "0",
            "DisplayLayoutColumn": "5",
            "LoadingPageType": "Right",
            "KinsPageNumber": "",
            "KinsPageName": "",
            "WorkStageNameKo": ""
        },
        {
            "ScenarioCode": "NW_DP_0009",
            "WorkflowName": "Print Customer Balance Statement",
            "WorkStageName": "",
            "DisplayLayoutRow": "0",
            "DisplayLayoutColumn": "6",
            "LoadingPageType": "Image",
            "KinsPageNumber": "UMS",
            "KinsPageName": "",
            "WorkStageNameKo": ""
        },
        {
            "ScenarioCode": "NW_DP_0009",
            "WorkflowName": "Print Customer Balance Statement",
            "WorkStageName": "",
            "DisplayLayoutRow": "0",
            "DisplayLayoutColumn": "7",
            "LoadingPageType": "Right",
            "KinsPageNumber": "",
            "KinsPageName": "",
            "WorkStageNameKo": ""
        },
        {
            "ScenarioCode": "NW_DP_0009",
            "WorkflowName": "Print Customer Balance Statement",
            "WorkStageName": "",
            "DisplayLayoutRow": "0",
            "DisplayLayoutColumn": "8",
            "LoadingPageType": "End",
            "KinsPageNumber": "",
            "KinsPageName": "",
            "WorkStageNameKo": ""
        },
        {
            "ScenarioCode": "NW_DP_0009",
            "WorkflowName": "Print Customer Balance Statement",
            "WorkStageName": "",
            "DisplayLayoutRow": "1",
            "DisplayLayoutColumn": "2",
            "LoadingPageType": "노",
            "KinsPageNumber": "",
            "KinsPageName": "",
            "WorkStageNameKo": ""
        },
        {
            "ScenarioCode": "NW_DP_0009",
            "WorkflowName": "Print Customer Balance Statement",
            "WorkStageName": "",
            "DisplayLayoutRow": "1",
            "DisplayLayoutColumn": "4",
            "LoadingPageType": "│",
            "KinsPageNumber": "",
            "KinsPageName": "",
            "WorkStageNameKo": ""
        },
        {
            "ScenarioCode": "NW_DP_0009",
            "WorkflowName": "Print Customer Balance Statement",
            "WorkStageName": "",
            "DisplayLayoutRow": "2",
            "DisplayLayoutColumn": "2",
            "LoadingPageType": "│",
            "KinsPageNumber": "",
            "KinsPageName": "",
            "WorkStageNameKo": ""
        },
        {
            "ScenarioCode": "NW_DP_0009",
            "WorkflowName": "Print Customer Balance Statement",
            "WorkStageName": "",
            "DisplayLayoutRow": "2",
            "DisplayLayoutColumn": "4",
            "LoadingPageType": "Picture",
            "KinsPageNumber": "137250",
            "KinsPageName": "",
            "WorkStageNameKo": ""
        },
        {
            "ScenarioCode": "NW_DP_0009",
            "WorkflowName": "Print Customer Balance Statement",
            "WorkStageName": "",
            "DisplayLayoutRow": "3",
            "DisplayLayoutColumn": "2",
            "LoadingPageType": "│",
            "KinsPageNumber": "",
            "KinsPageName": "",
            "WorkStageNameKo": ""
        },
        {
            "ScenarioCode": "NW_DP_0009",
            "WorkflowName": "Print Customer Balance Statement",
            "WorkStageName": "",
            "DisplayLayoutRow": "4",
            "DisplayLayoutColumn": "2",
            "LoadingPageType": "└",
            "KinsPageNumber": "",
            "KinsPageName": "",
            "WorkStageNameKo": ""
        },
        {
            "ScenarioCode": "NW_DP_0009",
            "WorkflowName": "Print Customer Balance Statement",
            "WorkStageName": "",
            "DisplayLayoutRow": "4",
            "DisplayLayoutColumn": "3",
            "LoadingPageType": "Right",
            "KinsPageNumber": "",
            "KinsPageName": "",
            "WorkStageNameKo": ""
        },
        {
            "ScenarioCode": "NW_DP_0009",
            "WorkflowName": "Print Customer Balance Statement",
            "WorkStageName": "(KR) 조회된 계좌 목록에서 잔액대사명세서 발송 대상 계좌를 단건 또는 복수건 선택 (EN) Select one or multiple Accounts From the retrieved Account List to send Customer Balance Statement ",
            "DisplayLayoutRow": "4",
            "DisplayLayoutColumn": "4",
            "LoadingPageType": "Image",
            "KinsPageNumber": "137250",
            "KinsPageName": "Customer Balance Statement",
            "WorkStageNameKo": ""
        },
        {
            "ScenarioCode": "NW_DP_0009",
            "WorkflowName": "Print Customer Balance Statement",
            "WorkStageName": "",
            "DisplayLayoutRow": "4",
            "DisplayLayoutColumn": "5",
            "LoadingPageType": "Right",
            "KinsPageNumber": "",
            "KinsPageName": "",
            "WorkStageNameKo": ""
        },
        {
            "ScenarioCode": "NW_DP_0009",
            "WorkflowName": "Print Customer Balance Statement",
            "WorkStageName": "UMS 발송 여부 ",
            "DisplayLayoutRow": "4",
            "DisplayLayoutColumn": "6",
            "LoadingPageType": "Fork",
            "KinsPageNumber": "",
            "KinsPageName": "",
            "WorkStageNameKo": ""
        },
        {
            "ScenarioCode": "NW_DP_0009",
            "WorkflowName": "Print Customer Balance Statement",
            "WorkStageName": "",
            "DisplayLayoutRow": "4",
            "DisplayLayoutColumn": "7",
            "LoadingPageType": "예",
            "KinsPageNumber": "",
            "KinsPageName": "",
            "WorkStageNameKo": ""
        },
        {
            "ScenarioCode": "NW_DP_0009",
            "WorkflowName": "Print Customer Balance Statement",
            "WorkStageName": "(KR) 선택된 잔액대사명세서 발송 대상 계좌 확인 후 UMS 버튼 클릭 (EN) After Confirming the Selected Accounts For Sending Customer Balance Statement, Click The UMS Button. ",
            "DisplayLayoutRow": "4",
            "DisplayLayoutColumn": "8",
            "LoadingPageType": "Image",
            "KinsPageNumber": "137250",
            "KinsPageName": "Customer Balance Statement",
            "WorkStageNameKo": ""
        },
        {
            "ScenarioCode": "NW_DP_0009",
            "WorkflowName": "Print Customer Balance Statement",
            "WorkStageName": "",
            "DisplayLayoutRow": "4",
            "DisplayLayoutColumn": "9",
            "LoadingPageType": "Right",
            "KinsPageNumber": "",
            "KinsPageName": "",
            "WorkStageNameKo": ""
        },
        {
            "ScenarioCode": "NW_DP_0009",
            "WorkflowName": "Print Customer Balance Statement",
            "WorkStageName": "",
            "DisplayLayoutRow": "4",
            "DisplayLayoutColumn": "10",
            "LoadingPageType": "Image",
            "KinsPageNumber": "UMS",
            "KinsPageName": "",
            "WorkStageNameKo": ""
        },
        {
            "ScenarioCode": "NW_DP_0009",
            "WorkflowName": "Print Customer Balance Statement",
            "WorkStageName": "",
            "DisplayLayoutRow": "4",
            "DisplayLayoutColumn": "11",
            "LoadingPageType": "Right",
            "KinsPageNumber": "",
            "KinsPageName": "",
            "WorkStageNameKo": ""
        },
        {
            "ScenarioCode": "NW_DP_0009",
            "WorkflowName": "Print Customer Balance Statement",
            "WorkStageName": "",
            "DisplayLayoutRow": "4",
            "DisplayLayoutColumn": "12",
            "LoadingPageType": "End",
            "KinsPageNumber": "",
            "KinsPageName": "",
            "WorkStageNameKo": ""
        },
        {
            "ScenarioCode": "NW_DP_0009",
            "WorkflowName": "Print Customer Balance Statement",
            "WorkStageName": "",
            "DisplayLayoutRow": "5",
            "DisplayLayoutColumn": "6",
            "LoadingPageType": "노",
            "KinsPageNumber": "",
            "KinsPageName": "",
            "WorkStageNameKo": ""
        },
        {
            "ScenarioCode": "NW_DP_0009",
            "WorkflowName": "Print Customer Balance Statement",
            "WorkStageName": "",
            "DisplayLayoutRow": "5",
            "DisplayLayoutColumn": "8",
            "LoadingPageType": "│",
            "KinsPageNumber": "",
            "KinsPageName": "",
            "WorkStageNameKo": ""
        },
        {
            "ScenarioCode": "NW_DP_0009",
            "WorkflowName": "Print Customer Balance Statement",
            "WorkStageName": "",
            "DisplayLayoutRow": "6",
            "DisplayLayoutColumn": "6",
            "LoadingPageType": "│",
            "KinsPageNumber": "",
            "KinsPageName": "",
            "WorkStageNameKo": ""
        },
        {
            "ScenarioCode": "NW_DP_0009",
            "WorkflowName": "Print Customer Balance Statement",
            "WorkStageName": "",
            "DisplayLayoutRow": "6",
            "DisplayLayoutColumn": "8",
            "LoadingPageType": "Picture",
            "KinsPageNumber": "137250",
            "KinsPageName": "",
            "WorkStageNameKo": ""
        },
        {
            "ScenarioCode": "NW_DP_0009",
            "WorkflowName": "Print Customer Balance Statement",
            "WorkStageName": "",
            "DisplayLayoutRow": "7",
            "DisplayLayoutColumn": "6",
            "LoadingPageType": "│",
            "KinsPageNumber": "",
            "KinsPageName": "",
            "WorkStageNameKo": ""
        },
        {
            "ScenarioCode": "NW_DP_0009",
            "WorkflowName": "Print Customer Balance Statement",
            "WorkStageName": "(KR) 선택된 잔액대사명세서 발송 대상 계좌 확인 후 Print 버튼 클릭 (EN) After Confirming the Selected Accounts For Sending Customer Balance Statement, Click The PRINT Button.  ",
            "DisplayLayoutRow": "8",
            "DisplayLayoutColumn": "6",
            "LoadingPageType": "Image",
            "KinsPageNumber": "137250",
            "KinsPageName": "Customer Balance Statement",
            "WorkStageNameKo": ""
        },
        {
            "ScenarioCode": "NW_DP_0009",
            "WorkflowName": "Print Customer Balance Statement",
            "WorkStageName": "",
            "DisplayLayoutRow": "8",
            "DisplayLayoutColumn": "7",
            "LoadingPageType": "Right",
            "KinsPageNumber": "",
            "KinsPageName": "",
            "WorkStageNameKo": ""
        },
        {
            "ScenarioCode": "NW_DP_0009",
            "WorkflowName": "Print Customer Balance Statement",
            "WorkStageName": "(베이징 지점) MT940 메시지 생성을 통한 계좌명세서 발송 여부 ",
            "DisplayLayoutRow": "8",
            "DisplayLayoutColumn": "8",
            "LoadingPageType": "Fork",
            "KinsPageNumber": "",
            "KinsPageName": "",
            "WorkStageNameKo": ""
        },
        {
            "ScenarioCode": "NW_DP_0009",
            "WorkflowName": "Print Customer Balance Statement",
            "WorkStageName": "",
            "DisplayLayoutRow": "8",
            "DisplayLayoutColumn": "9",
            "LoadingPageType": "예",
            "KinsPageNumber": "",
            "KinsPageName": "",
            "WorkStageNameKo": ""
        },
        {
            "ScenarioCode": "NW_DP_0009",
            "WorkflowName": "Print Customer Balance Statement",
            "WorkStageName": "(KR) 고객에게 출력한 잔액대사명세서를 Fax 또는 등기 발송 (EN) Send Customer Balance Statements to customers via Fax or Mail ",
            "DisplayLayoutRow": "8",
            "DisplayLayoutColumn": "10",
            "LoadingPageType": "Image",
            "KinsPageNumber": "수작업",
            "KinsPageName": "",
            "WorkStageNameKo": ""
        },
        {
            "ScenarioCode": "NW_DP_0009",
            "WorkflowName": "Print Customer Balance Statement",
            "WorkStageName": "",
            "DisplayLayoutRow": "9",
            "DisplayLayoutColumn": "6",
            "LoadingPageType": "│",
            "KinsPageNumber": "",
            "KinsPageName": "",
            "WorkStageNameKo": ""
        },
        {
            "ScenarioCode": "NW_DP_0009",
            "WorkflowName": "Print Customer Balance Statement",
            "WorkStageName": "",
            "DisplayLayoutRow": "9",
            "DisplayLayoutColumn": "8",
            "LoadingPageType": "노",
            "KinsPageNumber": "",
            "KinsPageName": "",
            "WorkStageNameKo": ""
        },
        {
            "ScenarioCode": "NW_DP_0009",
            "WorkflowName": "Print Customer Balance Statement",
            "WorkStageName": "",
            "DisplayLayoutRow": "9",
            "DisplayLayoutColumn": "10",
            "LoadingPageType": "│",
            "KinsPageNumber": "",
            "KinsPageName": "",
            "WorkStageNameKo": ""
        },
        {
            "ScenarioCode": "NW_DP_0009",
            "WorkflowName": "Print Customer Balance Statement",
            "WorkStageName": "",
            "DisplayLayoutRow": "10",
            "DisplayLayoutColumn": "6",
            "LoadingPageType": "Picture",
            "KinsPageNumber": "137250",
            "KinsPageName": "",
            "WorkStageNameKo": ""
        },
        {
            "ScenarioCode": "NW_DP_0009",
            "WorkflowName": "Print Customer Balance Statement",
            "WorkStageName": "",
            "DisplayLayoutRow": "10",
            "DisplayLayoutColumn": "8",
            "LoadingPageType": "└",
            "KinsPageNumber": "",
            "KinsPageName": "",
            "WorkStageNameKo": ""
        },
        {
            "ScenarioCode": "NW_DP_0009",
            "WorkflowName": "Print Customer Balance Statement",
            "WorkStageName": "",
            "DisplayLayoutRow": "10",
            "DisplayLayoutColumn": "9",
            "LoadingPageType": "━",
            "KinsPageNumber": "",
            "KinsPageName": "",
            "WorkStageNameKo": ""
        },
        {
            "ScenarioCode": "NW_DP_0009",
            "WorkflowName": "Print Customer Balance Statement",
            "WorkStageName": "",
            "DisplayLayoutRow": "10",
            "DisplayLayoutColumn": "10",
            "LoadingPageType": "End",
            "KinsPageNumber": "",
            "KinsPageName": "",
            "WorkStageNameKo": ""
        },
        {
            "ScenarioCode": "NW_DP_0010",
            "WorkflowName": "Print Balance Confirmation As Of Date",
            "WorkStageName": "(KR) 고객으로부터 월중 잔액현황 (원금 + 누적 이자금액) 확인 요청을 접수 (EN) Receive a customer's request to confirm balance as of date (principal + total accumulated interest amount) ",
            "DisplayLayoutRow": "0",
            "DisplayLayoutColumn": "0",
            "LoadingPageType": "Image",
            "KinsPageNumber": "수작업",
            "KinsPageName": "",
            "WorkStageNameKo": ""
        },
        {
            "ScenarioCode": "NW_DP_0010",
            "WorkflowName": "Print Balance Confirmation As Of Date",
            "WorkStageName": "",
            "DisplayLayoutRow": "0",
            "DisplayLayoutColumn": "1",
            "LoadingPageType": "Right",
            "KinsPageNumber": "",
            "KinsPageName": "",
            "WorkStageNameKo": ""
        },
        {
            "ScenarioCode": "NW_DP_0010",
            "WorkflowName": "Print Balance Confirmation As Of Date",
            "WorkStageName": "(KR) 계좌 번호, As Of Date 등을 기입하고 Inquiry 버튼을 클릭 (EN) Fill in information such as Account No. and As Of Date and press Inquiry button ",
            "DisplayLayoutRow": "0",
            "DisplayLayoutColumn": "2",
            "LoadingPageType": "Image",
            "KinsPageNumber": "00502_M",
            "KinsPageName": "Balance Confirmation As Of Date",
            "WorkStageNameKo": ""
        },
        {
            "ScenarioCode": "NW_DP_0010",
            "WorkflowName": "Print Balance Confirmation As Of Date",
            "WorkStageName": "",
            "DisplayLayoutRow": "0",
            "DisplayLayoutColumn": "3",
            "LoadingPageType": "Right",
            "KinsPageNumber": "",
            "KinsPageName": "",
            "WorkStageNameKo": ""
        },
        {
            "ScenarioCode": "NW_DP_0010",
            "WorkflowName": "Print Balance Confirmation As Of Date",
            "WorkStageName": "UMS 발송이 아닌 Print 후 수기 발송 여부 ",
            "DisplayLayoutRow": "0",
            "DisplayLayoutColumn": "4",
            "LoadingPageType": "Fork",
            "KinsPageNumber": "",
            "KinsPageName": "",
            "WorkStageNameKo": ""
        },
        {
            "ScenarioCode": "NW_DP_0010",
            "WorkflowName": "Print Balance Confirmation As Of Date",
            "WorkStageName": "",
            "DisplayLayoutRow": "0",
            "DisplayLayoutColumn": "5",
            "LoadingPageType": "No",
            "KinsPageNumber": "",
            "KinsPageName": "",
            "WorkStageNameKo": ""
        },
        {
            "ScenarioCode": "NW_DP_0010",
            "WorkflowName": "Print Balance Confirmation As Of Date",
            "WorkStageName": "(KR) 조회된 계좌 목록에서 잔액현황 확인서 발송 대상 계좌를 단건 또는 복수 선택 후 UMS 버튼 클릭 (EN) Select one or more entries from the list of accounts, and press UMS button to send Balance Confirmation As Of Date ",
            "DisplayLayoutRow": "0",
            "DisplayLayoutColumn": "6",
            "LoadingPageType": "Image",
            "KinsPageNumber": "00502_M",
            "KinsPageName": "Balance Confirmation As Of Date",
            "WorkStageNameKo": ""
        },
        {
            "ScenarioCode": "NW_DP_0010",
            "WorkflowName": "Print Balance Confirmation As Of Date",
            "WorkStageName": "",
            "DisplayLayoutRow": "0",
            "DisplayLayoutColumn": "7",
            "LoadingPageType": "Right",
            "KinsPageNumber": "",
            "KinsPageName": "",
            "WorkStageNameKo": ""
        },
        {
            "ScenarioCode": "NW_DP_0010",
            "WorkflowName": "Print Balance Confirmation As Of Date",
            "WorkStageName": "",
            "DisplayLayoutRow": "0",
            "DisplayLayoutColumn": "8",
            "LoadingPageType": "Image",
            "KinsPageNumber": "UMS",
            "KinsPageName": "",
            "WorkStageNameKo": ""
        },
        {
            "ScenarioCode": "NW_DP_0010",
            "WorkflowName": "Print Balance Confirmation As Of Date",
            "WorkStageName": "",
            "DisplayLayoutRow": "1",
            "DisplayLayoutColumn": "4",
            "LoadingPageType": "Yes",
            "KinsPageNumber": "",
            "KinsPageName": "",
            "WorkStageNameKo": ""
        },
        {
            "ScenarioCode": "NW_DP_0010",
            "WorkflowName": "Print Balance Confirmation As Of Date",
            "WorkStageName": "",
            "DisplayLayoutRow": "1",
            "DisplayLayoutColumn": "6",
            "LoadingPageType": "│",
            "KinsPageNumber": "",
            "KinsPageName": "",
            "WorkStageNameKo": ""
        },
        {
            "ScenarioCode": "NW_DP_0010",
            "WorkflowName": "Print Balance Confirmation As Of Date",
            "WorkStageName": "",
            "DisplayLayoutRow": "1",
            "DisplayLayoutColumn": "8",
            "LoadingPageType": "│",
            "KinsPageNumber": "",
            "KinsPageName": "",
            "WorkStageNameKo": ""
        },
        {
            "ScenarioCode": "NW_DP_0010",
            "WorkflowName": "Print Balance Confirmation As Of Date",
            "WorkStageName": "",
            "DisplayLayoutRow": "2",
            "DisplayLayoutColumn": "4",
            "LoadingPageType": "│",
            "KinsPageNumber": "",
            "KinsPageName": "",
            "WorkStageNameKo": ""
        },
        {
            "ScenarioCode": "NW_DP_0010",
            "WorkflowName": "Print Balance Confirmation As Of Date",
            "WorkStageName": "",
            "DisplayLayoutRow": "2",
            "DisplayLayoutColumn": "6",
            "LoadingPageType": "Picture",
            "KinsPageNumber": "00502_M",
            "KinsPageName": "",
            "WorkStageNameKo": ""
        },
        {
            "ScenarioCode": "NW_DP_0010",
            "WorkflowName": "Print Balance Confirmation As Of Date",
            "WorkStageName": "",
            "DisplayLayoutRow": "2",
            "DisplayLayoutColumn": "8",
            "LoadingPageType": "│",
            "KinsPageNumber": "",
            "KinsPageName": "",
            "WorkStageNameKo": ""
        },
        {
            "ScenarioCode": "NW_DP_0010",
            "WorkflowName": "Print Balance Confirmation As Of Date",
            "WorkStageName": "",
            "DisplayLayoutRow": "3",
            "DisplayLayoutColumn": "4",
            "LoadingPageType": "Down",
            "KinsPageNumber": "",
            "KinsPageName": "",
            "WorkStageNameKo": ""
        },
        {
            "ScenarioCode": "NW_DP_0010",
            "WorkflowName": "Print Balance Confirmation As Of Date",
            "WorkStageName": "",
            "DisplayLayoutRow": "3",
            "DisplayLayoutColumn": "8",
            "LoadingPageType": "Down",
            "KinsPageNumber": "",
            "KinsPageName": "",
            "WorkStageNameKo": ""
        },
        {
            "ScenarioCode": "NW_DP_0010",
            "WorkflowName": "Print Balance Confirmation As Of Date",
            "WorkStageName": "(KR) 조회된 계좌 목록에서 잔액현황 확인서 발송 대상 계좌를 단건 또는 복수 선택 후 Print 버튼 클릭 (EN) Select one or more entries from the list of accounts, and press Print button to print out Balance Confirmation As Of Date ",
            "DisplayLayoutRow": "4",
            "DisplayLayoutColumn": "4",
            "LoadingPageType": "Image",
            "KinsPageNumber": "00502_M",
            "KinsPageName": "Balance Confirmation As Of Date",
            "WorkStageNameKo": ""
        },
        {
            "ScenarioCode": "NW_DP_0010",
            "WorkflowName": "Print Balance Confirmation As Of Date",
            "WorkStageName": "",
            "DisplayLayoutRow": "4",
            "DisplayLayoutColumn": "5",
            "LoadingPageType": "Right",
            "KinsPageNumber": "",
            "KinsPageName": "",
            "WorkStageNameKo": ""
        },
        {
            "ScenarioCode": "NW_DP_0010",
            "WorkflowName": "Print Balance Confirmation As Of Date",
            "WorkStageName": "(KR) 고객 앞 잔액현황 확인서 송부 (via Fax, 우편 등) (EN) Send Balance Confirmation As Of Date to customer (via Fax, Mail, etc.) ",
            "DisplayLayoutRow": "4",
            "DisplayLayoutColumn": "6",
            "LoadingPageType": "Image",
            "KinsPageNumber": "수작업",
            "KinsPageName": "",
            "WorkStageNameKo": ""
        },
        {
            "ScenarioCode": "NW_DP_0010",
            "WorkflowName": "Print Balance Confirmation As Of Date",
            "WorkStageName": "",
            "DisplayLayoutRow": "4",
            "DisplayLayoutColumn": "7",
            "LoadingPageType": "Right",
            "KinsPageNumber": "",
            "KinsPageName": "",
            "WorkStageNameKo": ""
        },
        {
            "ScenarioCode": "NW_DP_0010",
            "WorkflowName": "Print Balance Confirmation As Of Date",
            "WorkStageName": "",
            "DisplayLayoutRow": "4",
            "DisplayLayoutColumn": "8",
            "LoadingPageType": "End",
            "KinsPageNumber": "",
            "KinsPageName": "",
            "WorkStageNameKo": ""
        },
        {
            "ScenarioCode": "NW_DP_0010",
            "WorkflowName": "Print Balance Confirmation As Of Date",
            "WorkStageName": "",
            "DisplayLayoutRow": "5",
            "DisplayLayoutColumn": "4",
            "LoadingPageType": "│",
            "KinsPageNumber": "",
            "KinsPageName": "",
            "WorkStageNameKo": ""
        },
        {
            "ScenarioCode": "NW_DP_0010",
            "WorkflowName": "Print Balance Confirmation As Of Date",
            "WorkStageName": "",
            "DisplayLayoutRow": "6",
            "DisplayLayoutColumn": "4",
            "LoadingPageType": "Picture",
            "KinsPageNumber": "00502_M",
            "KinsPageName": "",
            "WorkStageNameKo": ""
        },
        {
            "ScenarioCode": "NW_DP_0014",
            "WorkflowName": "Daily Deposit Balance Report Inquiry",
            "WorkStageName": "(KR) Account Group Kind, 고객 또는 계좌 번호를 입력하고 조회 버튼 클릭 (EN) Fill in Account Group Kind, Customer No or Account No, and press the arrow button ",
            "DisplayLayoutRow": "0",
            "DisplayLayoutColumn": "0",
            "LoadingPageType": "Image",
            "KinsPageNumber": "GSBQQA012R1",
            "KinsPageName": "",
            "WorkStageNameKo": ""
        },
        {
            "ScenarioCode": "NW_DP_0014",
            "WorkflowName": "Daily Deposit Balance Report Inquiry",
            "WorkStageName": "",
            "DisplayLayoutRow": "0",
            "DisplayLayoutColumn": "1",
            "LoadingPageType": "Right",
            "KinsPageNumber": "",
            "KinsPageName": "",
            "WorkStageNameKo": ""
        },
        {
            "ScenarioCode": "NW_DP_0014",
            "WorkflowName": "Daily Deposit Balance Report Inquiry",
            "WorkStageName": "(KR) 조회된 계좌별 예금 현황을 확인 (EN) Check Deposit accounts' balance, inflow and outflow information  ",
            "DisplayLayoutRow": "0",
            "DisplayLayoutColumn": "2",
            "LoadingPageType": "Image",
            "KinsPageNumber": "GSBQQA012R1",
            "KinsPageName": "",
            "WorkStageNameKo": ""
        },
        {
            "ScenarioCode": "NW_DP_0014",
            "WorkflowName": "Daily Deposit Balance Report Inquiry",
            "WorkStageName": "",
            "DisplayLayoutRow": "0",
            "DisplayLayoutColumn": "3",
            "LoadingPageType": "Right",
            "KinsPageNumber": "",
            "KinsPageName": "",
            "WorkStageNameKo": ""
        },
        {
            "ScenarioCode": "NW_DP_0014",
            "WorkflowName": "Daily Deposit Balance Report Inquiry",
            "WorkStageName": "",
            "DisplayLayoutRow": "0",
            "DisplayLayoutColumn": "4",
            "LoadingPageType": "End",
            "KinsPageNumber": "",
            "KinsPageName": "",
            "WorkStageNameKo": ""
        },
        {
            "ScenarioCode": "NW_DP_0014",
            "WorkflowName": "Daily Deposit Balance Report Inquiry",
            "WorkStageName": "",
            "DisplayLayoutRow": "1",
            "DisplayLayoutColumn": "0",
            "LoadingPageType": "│",
            "KinsPageNumber": "",
            "KinsPageName": "",
            "WorkStageNameKo": ""
        },
        {
            "ScenarioCode": "NW_DP_0014",
            "WorkflowName": "Daily Deposit Balance Report Inquiry",
            "WorkStageName": "",
            "DisplayLayoutRow": "2",
            "DisplayLayoutColumn": "0",
            "LoadingPageType": "Picture",
            "KinsPageNumber": "",
            "KinsPageName": "",
            "WorkStageNameKo": ""
        },
        {
            "ScenarioCode": "NW_DP_0019",
            "WorkflowName": "Inquire Account Transaction History",
            "WorkStageName": "",
            "DisplayLayoutRow": "0",
            "DisplayLayoutColumn": "0",
            "LoadingPageType": "Workflow",
            "KinsPageNumber": "NW_DP_0001",
            "KinsPageName": "",
            "WorkStageNameKo": ""
        },
        {
            "ScenarioCode": "NW_DP_0019",
            "WorkflowName": "Inquire Account Transaction History",
            "WorkStageName": "",
            "DisplayLayoutRow": "0",
            "DisplayLayoutColumn": "1",
            "LoadingPageType": "Right",
            "KinsPageNumber": "",
            "KinsPageName": "",
            "WorkStageNameKo": ""
        },
        {
            "ScenarioCode": "NW_DP_0019",
            "WorkflowName": "Inquire Account Transaction History",
            "WorkStageName": "(KR) 고객 및 계좌 번호, Transaction Date 등 조회 조건을 입력하고 Inquiry 버튼 클릭 (EN) Fill in information such as Customer No. and Account No.,Transaction Date, and press Inquiry button ",
            "DisplayLayoutRow": "0",
            "DisplayLayoutColumn": "2",
            "LoadingPageType": "Image",
            "KinsPageNumber": "137000",
            "KinsPageName": "Account Transaction History",
            "WorkStageNameKo": ""
        },
        {
            "ScenarioCode": "NW_DP_0019",
            "WorkflowName": "Inquire Account Transaction History",
            "WorkStageName": "",
            "DisplayLayoutRow": "0",
            "DisplayLayoutColumn": "3",
            "LoadingPageType": "Right",
            "KinsPageNumber": "",
            "KinsPageName": "",
            "WorkStageNameKo": ""
        },
        {
            "ScenarioCode": "NW_DP_0019",
            "WorkflowName": "Inquire Account Transaction History",
            "WorkStageName": "(KR) 조회된 결과 확인 및 보고서 출력을 위한 Print 버튼 클릭 (EN) Check the search results and click Print button to print out the Inquiry Deposit Account Transaction History report ",
            "DisplayLayoutRow": "0",
            "DisplayLayoutColumn": "4",
            "LoadingPageType": "Image",
            "KinsPageNumber": "137000",
            "KinsPageName": "Account Transaction History",
            "WorkStageNameKo": ""
        },
        {
            "ScenarioCode": "NW_DP_0019",
            "WorkflowName": "Inquire Account Transaction History",
            "WorkStageName": "",
            "DisplayLayoutRow": "0",
            "DisplayLayoutColumn": "5",
            "LoadingPageType": "Right",
            "KinsPageNumber": "",
            "KinsPageName": "",
            "WorkStageNameKo": ""
        },
        {
            "ScenarioCode": "NW_DP_0019",
            "WorkflowName": "Inquire Account Transaction History",
            "WorkStageName": "(KR) 조회된 결과 확인 및 보고서 출력을 위한 PrintForBank 버튼 클릭 (Account No. 기입 필수) (EN) Check the search results and click PrintForBank button to print out the Inquiry Deposit Account Transaction History report for to share with the customer (Account No. is mandatory) ",
            "DisplayLayoutRow": "0",
            "DisplayLayoutColumn": "6",
            "LoadingPageType": "Image",
            "KinsPageNumber": "137000",
            "KinsPageName": "Account Transaction History",
            "WorkStageNameKo": ""
        },
        {
            "ScenarioCode": "NW_DP_0019",
            "WorkflowName": "Inquire Account Transaction History",
            "WorkStageName": "",
            "DisplayLayoutRow": "0",
            "DisplayLayoutColumn": "7",
            "LoadingPageType": "Right",
            "KinsPageNumber": "",
            "KinsPageName": "",
            "WorkStageNameKo": ""
        },
        {
            "ScenarioCode": "NW_DP_0019",
            "WorkflowName": "Inquire Account Transaction History",
            "WorkStageName": "",
            "DisplayLayoutRow": "0",
            "DisplayLayoutColumn": "8",
            "LoadingPageType": "End",
            "KinsPageNumber": "",
            "KinsPageName": "",
            "WorkStageNameKo": ""
        },
        {
            "ScenarioCode": "NW_DP_0019",
            "WorkflowName": "Inquire Account Transaction History",
            "WorkStageName": "",
            "DisplayLayoutRow": "1",
            "DisplayLayoutColumn": "4",
            "LoadingPageType": "│",
            "KinsPageNumber": "",
            "KinsPageName": "",
            "WorkStageNameKo": ""
        },
        {
            "ScenarioCode": "NW_DP_0019",
            "WorkflowName": "Inquire Account Transaction History",
            "WorkStageName": "",
            "DisplayLayoutRow": "1",
            "DisplayLayoutColumn": "6",
            "LoadingPageType": "│",
            "KinsPageNumber": "",
            "KinsPageName": "",
            "WorkStageNameKo": ""
        },
        {
            "ScenarioCode": "NW_DP_0019",
            "WorkflowName": "Inquire Account Transaction History",
            "WorkStageName": "",
            "DisplayLayoutRow": "2",
            "DisplayLayoutColumn": "4",
            "LoadingPageType": "Picture",
            "KinsPageNumber": "137000",
            "KinsPageName": "",
            "WorkStageNameKo": ""
        },
        {
            "ScenarioCode": "NW_DP_0019",
            "WorkflowName": "Inquire Account Transaction History",
            "WorkStageName": "",
            "DisplayLayoutRow": "2",
            "DisplayLayoutColumn": "6",
            "LoadingPageType": "Picture",
            "KinsPageNumber": "137000",
            "KinsPageName": "",
            "WorkStageNameKo": ""
        },
        {
            "ScenarioCode": "NW_DP_0020",
            "WorkflowName": "Inquire Interest",
            "WorkStageName": "(KR) 고객 및 계좌 번호 등 조회 조건을 입력하고 Inquiry 버튼 클릭 (EN) Fill in information such as Customer No. and Account No., and press Inquiry button ",
            "DisplayLayoutRow": "0",
            "DisplayLayoutColumn": "0",
            "LoadingPageType": "Image",
            "KinsPageNumber": "137500",
            "KinsPageName": "Interest Payment",
            "WorkStageNameKo": ""
        },
        {
            "ScenarioCode": "NW_DP_0020",
            "WorkflowName": "Inquire Interest",
            "WorkStageName": "",
            "DisplayLayoutRow": "0",
            "DisplayLayoutColumn": "1",
            "LoadingPageType": "Right",
            "KinsPageNumber": "",
            "KinsPageName": "",
            "WorkStageNameKo": ""
        },
        {
            "ScenarioCode": "NW_DP_0020",
            "WorkflowName": "Inquire Interest",
            "WorkStageName": "(KR) 조회된 결과 확인 및 보고서 출력을 위한 Print 버튼 클릭 (EN) Check the search results and click Print button to print out the Inquiry Payment of Interest report ",
            "DisplayLayoutRow": "0",
            "DisplayLayoutColumn": "2",
            "LoadingPageType": "Image",
            "KinsPageNumber": "137500",
            "KinsPageName": "Interest Payment",
            "WorkStageNameKo": ""
        },
        {
            "ScenarioCode": "NW_DP_0020",
            "WorkflowName": "Inquire Interest",
            "WorkStageName": "",
            "DisplayLayoutRow": "0",
            "DisplayLayoutColumn": "3",
            "LoadingPageType": "Right",
            "KinsPageNumber": "",
            "KinsPageName": "",
            "WorkStageNameKo": ""
        },
        {
            "ScenarioCode": "NW_DP_0020",
            "WorkflowName": "Inquire Interest",
            "WorkStageName": "(KR) 이자계산서를 작성하여 고객에게 우편으로 발송 (EN) After interest payment, generate an interest statement and send it to the customer by mail ",
            "DisplayLayoutRow": "0",
            "DisplayLayoutColumn": "4",
            "LoadingPageType": "Image",
            "KinsPageNumber": "수작업",
            "KinsPageName": "",
            "WorkStageNameKo": ""
        },
        {
            "ScenarioCode": "NW_DP_0020",
            "WorkflowName": "Inquire Interest",
            "WorkStageName": "",
            "DisplayLayoutRow": "0",
            "DisplayLayoutColumn": "5",
            "LoadingPageType": "Right",
            "KinsPageNumber": "",
            "KinsPageName": "",
            "WorkStageNameKo": ""
        },
        {
            "ScenarioCode": "NW_DP_0020",
            "WorkflowName": "Inquire Interest",
            "WorkStageName": "",
            "DisplayLayoutRow": "0",
            "DisplayLayoutColumn": "6",
            "LoadingPageType": "End",
            "KinsPageNumber": "",
            "KinsPageName": "",
            "WorkStageNameKo": ""
        },
        {
            "ScenarioCode": "NW_DP_0020",
            "WorkflowName": "Inquire Interest",
            "WorkStageName": "",
            "DisplayLayoutRow": "1",
            "DisplayLayoutColumn": "2",
            "LoadingPageType": "│",
            "KinsPageNumber": "",
            "KinsPageName": "",
            "WorkStageNameKo": ""
        },
        {
            "ScenarioCode": "NW_DP_0020",
            "WorkflowName": "Inquire Interest",
            "WorkStageName": "",
            "DisplayLayoutRow": "2",
            "DisplayLayoutColumn": "2",
            "LoadingPageType": "Picture",
            "KinsPageNumber": "137500",
            "KinsPageName": "",
            "WorkStageNameKo": ""
        },
        {
            "ScenarioCode": "NW_DP_0023",
            "WorkflowName": "Inquire High Risk/Important Account ",
            "WorkStageName": "(KR) 고객 및 계좌 번호 등 조회 조건을 입력하고 Inquiry 버튼 클릭 (EN) Fill in information such as Customer No. and Account No., and press Inquiry button ",
            "DisplayLayoutRow": "0",
            "DisplayLayoutColumn": "0",
            "LoadingPageType": "Image",
            "KinsPageNumber": "00503_M",
            "KinsPageName": "High Risk/Important Account List",
            "WorkStageNameKo": ""
        },
        {
            "ScenarioCode": "NW_DP_0023",
            "WorkflowName": "Inquire High Risk/Important Account ",
            "WorkStageName": "",
            "DisplayLayoutRow": "0",
            "DisplayLayoutColumn": "1",
            "LoadingPageType": "Right",
            "KinsPageNumber": "",
            "KinsPageName": "",
            "WorkStageNameKo": ""
        },
        {
            "ScenarioCode": "NW_DP_0023",
            "WorkflowName": "Inquire High Risk/Important Account ",
            "WorkStageName": "(KR) 조회된 결과에서 고위험/중요 계좌로 분류된 계좌 목록 확인 (EN) Check the search results for the accounts classified as High Risk/Important ",
            "DisplayLayoutRow": "0",
            "DisplayLayoutColumn": "2",
            "LoadingPageType": "Image",
            "KinsPageNumber": "00503_M",
            "KinsPageName": "High Risk/Important Account List",
            "WorkStageNameKo": ""
        },
        {
            "ScenarioCode": "NW_DP_0023",
            "WorkflowName": "Inquire High Risk/Important Account ",
            "WorkStageName": "",
            "DisplayLayoutRow": "0",
            "DisplayLayoutColumn": "3",
            "LoadingPageType": "Right",
            "KinsPageNumber": "",
            "KinsPageName": "",
            "WorkStageNameKo": ""
        },
        {
            "ScenarioCode": "NW_DP_0023",
            "WorkflowName": "Inquire High Risk/Important Account ",
            "WorkStageName": "",
            "DisplayLayoutRow": "0",
            "DisplayLayoutColumn": "4",
            "LoadingPageType": "End",
            "KinsPageNumber": "",
            "KinsPageName": "",
            "WorkStageNameKo": ""
        }
    ]
}